maze_game_engine/Markers.py
maze_game_engine/Maze.py
maze_game_engine/__init__.py
maze_game_engine/MazeObjects/Agent.py
maze_game_engine/MazeObjects/PointOfInterest.py
maze_game_engine/MazeObjects/User.py
maze_game_engine/Utilities/Environment.py
maze_game_engine-0.1.dist-info/licenses/LICENSE
maze_game_engine-0.1.dist-info/METADATA
maze_game_engine-0.1.dist-info/WHEEL
maze_game_engine-0.1.dist-info/top_level.txt
maze_game_engine-0.1.dist-info/RECORD
