Metadata-Version: 2.4
Name: maze-game-engine
Version: 0.1
Summary: A basic engine for basic maze games.
Author-email: "Nel. S." <75831544+Nel-S@users.noreply.github.com>
License-Expression: CC-BY-NC-SA-4.0
Project-URL: Homepage, https://github.com/Nel-S/Maze
Project-URL: Issues, https://github.com/Nel-S/Maze/issues
Classifier: Development Status :: 3 - Alpha
Classifier: Environment :: Console
Classifier: Natural Language :: English
Classifier: Operating System :: OS Independent
Classifier: Programming Language :: Python :: 3
Classifier: Typing :: Typed
Requires-Python: >=3.10
License-File: LICENSE
Requires-Dist: numpy
Dynamic: license-file
